flasdev/__init__.py
flasdev/install.py
flaskdev-0.0.1.dist-info/METADATA
flaskdev-0.0.1.dist-info/WHEEL
flaskdev-0.0.1.dist-info/entry_points.txt
flaskdev-0.0.1.dist-info/top_level.txt
flaskdev-0.0.1.dist-info/RECORD
