Metadata-Version: 2.1
Name: flaskdev
Version: 0.0.1
Summary: Tool to create a basic Flask project structure
Author: Daniel Beukes
